main.py
google_img_source_search/__init__.py
google_img_source_search/batchexecute_decoder.py
google_img_source_search/exceptions.py
google_img_source_search/f_req_template.py
google_img_source_search/image_file_uploader.py
google_img_source_search/image_source_searcher.py
google_img_source_search/image_uploader.py
google_img_source_search/reverse_image_searcher.py
google_img_source_search/safe_modes.py
google_img_source_search/google_items/__init__.py
google_img_source_search/google_items/image.py
google_img_source_search/google_items/search_item.py
google_image_source_search-1.2.2.dist-info/LICENSE
google_image_source_search-1.2.2.dist-info/METADATA
google_image_source_search-1.2.2.dist-info/WHEEL
google_image_source_search-1.2.2.dist-info/top_level.txt
google_image_source_search-1.2.2.dist-info/RECORD
