Metadata-Version: 2.1
Name: google-image-source-search
Version: 1.2.2
Summary: A package to search image sources using google services
Author-email: Vorrik <author@example.com>
Project-URL: Homepage, https://github.com/Vorrik/Google-Image-Source-Search
Project-URL: Bug Tracker, https://github.com/Vorrik/Google-Image-Source-Search/issues
Classifier: Programming Language :: Python :: 3
Classifier: License :: OSI Approved :: MIT License
Classifier: Operating System :: OS Independent
Requires-Python: >=3.7
License-File: LICENSE
Requires-Dist: requests<=2.31.0
